setup.py
snailhelper/__init__.py
snailhelper/cachehelper.py
snailhelper/confighelper.py
snailhelper/datehelper.py
snailhelper/httphelper.py
snailhelper.egg-info/PKG-INFO
snailhelper.egg-info/SOURCES.txt
snailhelper.egg-info/dependency_links.txt
snailhelper.egg-info/top_level.txt